pycounts_gf/__init__.py
pycounts_gf/plotting.py
pycounts_gf/pycounts_gf.py
pycounts_gf-1.0.dist-info/LICENSE
pycounts_gf-1.0.dist-info/WHEEL
pycounts_gf-1.0.dist-info/METADATA
pycounts_gf-1.0.dist-info/RECORD
