Metadata-Version: 2.1
Name: pycounts-gf
Version: 1.0
Summary: Count the number of occurrences of a word in a text file
License: MIT
Author: Gabriel Fairbrother
Requires-Python: >=3.9,<4.0
Classifier: License :: OSI Approved :: MIT License
Classifier: Programming Language :: Python :: 3
Classifier: Programming Language :: Python :: 3.10
Classifier: Programming Language :: Python :: 3.9
Requires-Dist: matplotlib (>=3.5.1,<4.0.0)
